sendy/__init__.py
sendy/api.py
sendy-0.1.dist-info/LICENSE.txt
sendy-0.1.dist-info/METADATA
sendy-0.1.dist-info/WHEEL
sendy-0.1.dist-info/top_level.txt
sendy-0.1.dist-info/RECORD
